LICENSE
README.md
lyylog2.py
setup.py
lyylog2.egg-info/PKG-INFO
lyylog2.egg-info/SOURCES.txt
lyylog2.egg-info/dependency_links.txt
lyylog2.egg-info/top_level.txt