Metadata-Version: 2.1
Name: lyylog2
Version: 1.17
Summary: lyylog2 for lyy
Author: lyy
Author-email: 
License: MIT
License-File: LICENSE
